opentelemetry_instrumentation_kstreams/__init__.py
opentelemetry_instrumentation_kstreams/instrumentor.py
opentelemetry_instrumentation_kstreams/middlewares.py
opentelemetry_instrumentation_kstreams/package.py
opentelemetry_instrumentation_kstreams/py.typed
opentelemetry_instrumentation_kstreams/utils.py
opentelemetry_instrumentation_kstreams/version.py
opentelemetry_instrumentation_kstreams/wrappers.py
opentelemetry_instrumentation_kstreams-0.5.1.dist-info/METADATA
opentelemetry_instrumentation_kstreams-0.5.1.dist-info/WHEEL
opentelemetry_instrumentation_kstreams-0.5.1.dist-info/entry_points.txt
opentelemetry_instrumentation_kstreams-0.5.1.dist-info/licenses/LICENSE.md
opentelemetry_instrumentation_kstreams-0.5.1.dist-info/RECORD
